preview/__init__.py
preview/__main__.py
preview/file_monitor.py
preview/handlers.py
preview/utils.py
filepreviewer-4.0.dist-info/METADATA
filepreviewer-4.0.dist-info/WHEEL
filepreviewer-4.0.dist-info/entry_points.txt
filepreviewer-4.0.dist-info/RECORD
