Metadata-Version: 2.1
Name: filepreviewer
Version: 4.0
Summary: 
Author: CD Clark III
Author-email: clifton.clark@gmail.com
Requires-Python: >=3.10,<4.0
Classifier: Programming Language :: Python :: 3
Classifier: Programming Language :: Python :: 3.10
Classifier: Programming Language :: Python :: 3.11
Requires-Dist: pymsgbox (>=1.0.9,<2.0.0)
Requires-Dist: typer (>=0.7.0,<0.8.0)
Requires-Dist: watchdog (>=2.2.1,<3.0.0)
